Maddex/__init__.py
Maddex/data.py
MaddexScanner-1.0.6.dist-info/LICENSE
MaddexScanner-1.0.6.dist-info/METADATA
MaddexScanner-1.0.6.dist-info/WHEEL
MaddexScanner-1.0.6.dist-info/top_level.txt
MaddexScanner-1.0.6.dist-info/RECORD
