Metadata-Version: 2.1
Name: MaddexScanner
Version: 1.0.6
Summary: Maddex Scanner module repo.
Home-page: https://github.com/Wizard
Author: ShhWizard
Author-email: cpjojowat007@gmail.com
License: GNU General Public License v3.0
Keywords: telegram,Maddex,scanner,pyrogram
Classifier: Framework :: AsyncIO
Classifier: Development Status :: 3 - Alpha
Classifier: Intended Audience :: Developers
Classifier: License :: OSI Approved :: GNU General Public License v2 or later (GPLv2+)
Classifier: Natural Language :: English
Classifier: Operating System :: OS Independent
Classifier: Programming Language :: Python :: 3.7
Classifier: Programming Language :: Python :: 3.8
Classifier: Programming Language :: Python :: 3.9
Classifier: Programming Language :: Python :: 3.10
Classifier: Topic :: Internet :: WWW/HTTP
Classifier: Topic :: Software Development :: Libraries
Classifier: Topic :: Software Development :: Build Tools
License-File: LICENSE
Requires-Dist: sqlalchemy (==1.3.20)
Requires-Dist: psycopg2-binary
